yogasmara_addon/__init__.py
yogasmara_addon/septiana_yogasmara_addon.py
yogasmara_pkg_septiana_yogasmara-0.1.0.dist-info/METADATA
yogasmara_pkg_septiana_yogasmara-0.1.0.dist-info/WHEEL
yogasmara_pkg_septiana_yogasmara-0.1.0.dist-info/top_level.txt
yogasmara_pkg_septiana_yogasmara-0.1.0.dist-info/RECORD
