Metadata-Version: 2.1
Name: yogasmara-pkg-septiana-yogasmara
Version: 0.1.0
Summary: Yogasmara Python script build for blender
Home-page: https://github.com/yoga1234/yogasmara-addon
Author: Septiana Yogasmara
Author-email: septianayoga30@gmail.com
License: UNKNOWN
Platform: UNKNOWN
Classifier: Programming Language :: Python :: 3
Classifier: License :: OSI Approved :: MIT License
Classifier: Operating System :: OS Independent
